{
  "contentType": "Page",
  "navigationBar": {
    "pageTitle": "Societal Platform SPace",
    "pageBackLink": "none",
    "background": {
      "color": "default",
      "styles": {
        "background-color": "white",
        "color": "#333"
      }
    },
    "xsmallNonMenuLinks": [
      {
        "widgetType": "actionButton",
        "widgetSubType": "buttonFeature",
        "widgetData": {
          "actionBtnId": "feature_notification",
          "config": {
            "type": "mat-icon-button"
          }
        }
      }
    ],
    "links": [
      {
        "widgetType": "actionButton",
        "widgetSubType": "buttonFeature",
        "widgetData": {
          "actionBtnId": "feature_knowledgeBoard",
          "config": {
            "type": "mat-button"
          }
        }
      },
      {
        "widgetType": "actionButton",
        "widgetSubType": "buttonFeature",
        "widgetData": {
          "actionBtnId": "feature_channels",
          "config": {
            "type": "mat-button"
          }
        }
      },
      {
        "widgetType": "actionButton",
        "widgetSubType": "buttonFeature",
        "widgetData": {
          "actionBtnId": "feature_learningJourney",
          "config": {
            "type": "mat-button"
          }
        }
      }
    ]
  },
  "pageLayout": {
    "widgetSubType": "gridLayout",
    "widgetType": "layout",
    "widgetData": {
      "widgets": [
        [
          {
            "dimensions": {},
            "widget": {
              "widgetType": "slider",
              "widgetSubType": "sliderBanners",
              "widgetData": [
                {
                  "banners": {
                    "l": "assets/instances/space/banners/MainBanner-1366x250.png",
                    "m": "assets/instances/space/banners/MainBanner-1024x250.png",
                    "s": "assets/instances/space/banners/MainBanner-768x250.png",
                    "xl": "assets/instances/space/banners/MainBanner-1920x250.png",
                    "xs": "assets/instances/space/banners/MainBanner-414x250.png",
                    "xxl": "assets/instances/space/banners/MainBanner-2850x250.png"
                  },
                  "redirectUrl": "/app/search/learning",
                  "queryParams": {
                    "q": "all",
                    "lang": "en",
                    "f": ""
                  },
                  "title": "",
                  "sliderInterval": 4000
                }
              ]
            }
          },
          {
            "dimensions": {},
            "widget": {
              "widgetType": "card",
              "widgetSubType": "cardWelcome",
              "widgetData": {}
            }
          }
        ],
        [
          {
            "dimensions": {},
            "widget": {
              "widgetType": "contentStrip",
              "widgetSubType": "contentStripMultiple",
              "widgetData": {
                "strips": [
                  {
                    "key": "latest",
                    "title": "Latest",
                    "info": {
                      "mode": "below",
                      "visibilityMode": "hidden",
                      "icon": {
                        "icon": "info",
                        "scale": 0.8
                      },
                      "widget": {
                        "widgetType": "element",
                        "widgetSubType": "elementHtml",
                        "widgetData": {
                          "html": "<p class=\"ws-mat-primary-text\">Here you’ll find the very latest learning opportunities.</p>"
                        }
                      }
                    },
                    "stripConfig": {
                      "cardSubType": "standard",
                      "intranetMode": "hide",
                      "deletedMode": "hide"
                    },
                    "filters": {},
                    "request": {
                      "api": {
                        "path": "/apis/protected/v8/recommendation/latest",
                        "queryParams": {
                          "pageNo": 0,
                          "pageSize": 15
                        }
                      }
                    }
                  }
                ]
              }
            }
          }
        ],
        [
          {
            "dimensions": {},
            "widget": {
              "widgetType": "contentStrip",
              "widgetSubType": "contentStripMultiple",
              "widgetData": {
                "strips": [
                  {
                    "key": "interestBased",
                    "title": "Based on your interests",
                    "info": {
                      "mode": "below",
                      "visibilityMode": "hidden",
                      "icon": {
                        "icon": "info",
                        "scale": 0.8
                      },
                      "widget": {
                        "widgetType": "element",
                        "widgetSubType": "elementHtml",
                        "widgetData": {
                          "html": "<p class=\"ws-mat-primary-text\">This is where we'll show you the most relevant learning opportunities, based on the interests you've chosen. </p>"
                        }
                      }
                    },
                    "stripConfig": {
                      "cardSubType": "standard"
                    },
                    "filters": [],
                    "noDataWidget": {
                      "widgetType": "element",
                      "widgetSubType": "elementHtml",
                      "widgetData": {
                        "html": "<div class=\"flex justify-between items-center\"><p class=\"ws-mat-primary-text margin-remove margin-right-xs\">Please add or modify your interest topics to find relevant content. </p><a class=\"mat-flat-button mat-primary\" style=\"color:white\" onclick=\"window.navigateTo(`/app/profile/interest`)\">Edit</a></div>"
                      }
                    },
                    "request": {
                      "api": {
                        "path": "/apis/protected/v8/recommendation/interestBased",
                        "queryParams": {
                          "pageNo": 0,
                          "pageSize": 15
                        }
                      }
                    }
                  }
                ]
              }
            }
          }
        ],
        [
          {
            "dimensions": {
              "small": 12,
              "medium": 12
            },
            "widget": {
              "widgetType": "contentStrip",
              "widgetSubType": "contentStripMultiple",
              "widgetData": {
                "strips": [
                  {
                    "key": "continueLearning",
                    "title": "Last viewed",
                    "noDataWidget": {
                      "widgetType": "element",
                      "widgetSubType": "elementHtml",
                      "widgetData": {
                        "html": "<p class=\"ws-mat-primary-text\">Learning activities you start will appear here.</p>"
                      }
                    },
                    "info": {
                      "mode": "below",
                      "visibilityMode": "hidden",
                      "icon": {
                        "icon": "info",
                        "scale": 0.8
                      },
                      "widget": {
                        "widgetType": "element",
                        "widgetSubType": "elementHtml",
                        "widgetData": {
                          "html": "<p class=\"ws-mat-primary-text\">These are the learning activities you’ve started but haven’t finished yet. Ready to keep going?</p>"
                        }
                      }
                    },
                    "stripConfig": {
                      "cardSubType": "standard"
                    },
                    "filters": [],
                    "request": {
                      "api": {
                        "path": "/apis/protected/v8/user/history",
                        "queryParams": {
                          "pageSize": 20
                        }
                      }
                    }
                  }
                ]
              }
            }
          }
        ],
        [
          {
            "dimensions": {
              "small": 12,
              "medium": 12
            },
            "widget": {
              "widgetType": "contentStrip",
              "widgetSubType": "contentStripMultiple",
              "widgetData": {
                "strips": [
                  {
                    "key": "recentToPlaylists",
                    "title": "From your playlists",
                    "noDataWidget": {
                      "widgetType": "element",
                      "widgetSubType": "elementHtml",
                      "widgetData": {
                        "html": "<p class=\"ws-mat-primary-text\">Your latest content added to a playlist appears here.</p>"
                      }
                    },
                    "info": {
                      "mode": "below",
                      "visibilityMode": "hidden",
                      "icon": {
                        "icon": "info",
                        "scale": 0.8
                      },
                      "widget": {
                        "widgetType": "element",
                        "widgetSubType": "elementHtml",
                        "widgetData": {
                          "html": "<p class=\"ws-mat-primary-text\">Seen something you want to check out or share later? Add it to your playlist and we’ll keep it here.</p>"
                        }
                      }
                    },
                    "stripConfig": {
                      "cardSubType": "standard"
                    },
                    "filters": [],
                    "request": {
                      "api": {
                        "path": "/apis/protected/v8/user/playlist/recent"
                      }
                    },
                    "refreshEvent": {
                      "eventType": "Action",
                      "from": "actionButton/actionButtonPlaylist"
                    }
                  }
                ]
              }
            }
          }
        ]
      ]
    }
  }
}
